xsscan/__init__.py
xsscan/cli/__init__.py
xsscan/cli/main.py
xsscan/config/__init__.py
xsscan/config/manager.py
xsscan/core/__init__.py
xsscan/core/crawler.py
xsscan/core/detector.py
xsscan/core/models.py
xsscan/core/payloads.py
xsscan/core/scanner.py
xsscan/reporting/__init__.py
xsscan/reporting/export.py
xsscan-1.0.0.dist-info/licenses/LICENSE
xsscan-1.0.0.dist-info/METADATA
xsscan-1.0.0.dist-info/WHEEL
xsscan-1.0.0.dist-info/entry_points.txt
xsscan-1.0.0.dist-info/top_level.txt
xsscan-1.0.0.dist-info/RECORD
