Metadata-Version: 2.4
Name: xsscan
Version: 1.0.0
Summary: Production-grade CLI tool for detecting Cross-Site Scripting (XSS) vulnerabilities
Author-email: Alan <whoamialan11@gmail.com>
License-Expression: MIT
Project-URL: Homepage, https://github.com/xsscan/xsscan
Project-URL: Documentation, https://github.com/xsscan/xsscan#readme
Project-URL: Repository, https://github.com/xsscan/xsscan
Project-URL: Issues, https://github.com/xsscan/xsscan/issues
Keywords: security,xss,vulnerability,scanner,pentesting
Classifier: Development Status :: 4 - Beta
Classifier: Intended Audience :: Developers
Classifier: Intended Audience :: Information Technology
Classifier: Topic :: Security
Classifier: Programming Language :: Python :: 3
Classifier: Programming Language :: Python :: 3.8
Classifier: Programming Language :: Python :: 3.9
Classifier: Programming Language :: Python :: 3.10
Classifier: Programming Language :: Python :: 3.11
Classifier: Programming Language :: Python :: 3.12
Requires-Python: >=3.8
License-File: LICENSE
Requires-Dist: typer>=0.9.0
Requires-Dist: rich>=13.0.0
Requires-Dist: httpx>=0.24.0
Requires-Dist: beautifulsoup4>=4.12.0
Requires-Dist: lxml>=4.9.0
Requires-Dist: reportlab>=4.0.0
Requires-Dist: pydantic>=2.0.0
Requires-Dist: pyyaml>=6.0.0
Requires-Dist: appdirs>=1.4.4
Dynamic: license-file
